Workbook

Sheet Leia-me
B1: EDITAL VERTICALIZADO TCE-GO 2026 - CARGO B02 (TECNICO DE CONTROLE EXTERNO: TI) - VERSAO 2.0
B3: O que ha de novo nesta versao
B4: Duas colunas foram adicionadas a aba Edital Verticalizado: Incidencia Historica e Prioridade. Elas resumem a analise de 9 provas FCC: 8 provas de Tecnico Judiciario TI de TRTs (2010 a 2017) e a prova do TCE-GO 2022 (Analista de Controle Externo TI), o material mais proximo do seu concurso por reunir mesma banca e mesmo orgao.
B5: A coluna Status desta versao vem zerada (Nao estudado). Se voce ja tinha marcacoes na versao anterior, copie a coluna para ca ou envie o arquivo antigo para mesclagem.
B7: Como ler a coluna Incidencia Historica
B8: Ela indica quantas vezes o assunto apareceu nas 9 provas analisadas, com destaque para o que caiu na prova TCE-GO 2022 (citada por numero de questao). Quando o tema nunca caiu, a celula informa que e estreia do edital 2026: nesses casos nao existe historico FCC para calibrar, e a prioridade foi definida pela relevancia e pelo volume do tema no edital.
B10: Niveis de prioridade
B11: URGENTE: temas com cobranca recorrente comprovada pela banca e que permanecem no edital 2026, ou estreias de altissima probabilidade. Sao a base da nota. Estude primeiro e mantenha em revisao continua.
B12: ALTA: temas com bom historico de cobranca ou estreias com grande volume no edital e forte apelo para a banca. Entram no ciclo logo apos os urgentes.
B13: MEDIA: temas com cobranca esparsa ou escopo menor. Devem ser cobertos, mas sem roubar horas dos niveis acima.
B14: BAIXA: temas perifericos, sem historico e com baixo potencial de questao. Cubra ao final ou em revisoes rapidas.
B16: Criterios usados na classificacao
... B29: Itens marcados com [Interpretacao] decompoem o texto literal do edital para facilitar o estudo, sem extrapolar o escopo.

Sheet Edital Verticalizado
A1: Nº | B1: Bloco | C1: Peso | D1: Disciplina | E1: Item de Estudo | F1: Incidência Histórica (9 provas FCC) | G1: Prioridade | H1: Status | I1: Anotações
A2: 1 | B2: CG | C2: 1 | D2: Lingua Portuguesa | E2: Redacao Oficial | F2: Pouco cobrada nas provas analisadas; item novo no CG 2026 | G2: Média | H2: Não estudado
A3: 2 | B3: CG | C3: 1 | D3: Lingua Portuguesa | E3: Ortografia e acentuacao | F3: Presenca constante no bloco de portugues FCC | G3: Alta | H3: Não estudado
A4: 3 | B4: CG | C4: 1 | D4: Lingua Portuguesa | E4: Emprego do sinal indicativo de crase | F4: Classico FCC; aparece em quase toda prova de portugues | G4: Alta | H4: Não estudado
A5: 4 | B5: CG | C5: 1 | D5: Lingua Portuguesa | E5: Compreensao e interpretacao de textos de generos variados | F5: Maior fatia do bloco: 25 questoes de portugues na prova TCE-GO 2022 | G5: Urgente | H5: Não estudado
A6: 5 | B6: CG | C6: 1 | D6: Lingua Portuguesa | E6: Relacao do texto com seu contexto historico | F6: Cobranca eventual, associada a interpretacao | G6: Baixa | H6: Não estudado
A7: 6 | B7: CG | C7: 1 | D7: Lingua Portuguesa | E7: Denotacao e conotacao | F7: Cobranca eventual em interpretacao | G7: Média | H7: Não estudado
A8: 7 | B8: CG | C8: 1 | D8: Lingua Portuguesa | E8: Discurso direto, indireto e indireto livre | F8: Cobranca eventual no padrao FCC | G8: Média | H8: Não estudado
A9: 8 | B9: CG | C9: 1 | D9: Lingua Portuguesa | E9: Intertextualidade | F9: Cobranca eventual em interpretacao | G9: Baixa | H9: Não estudado
A10: 9 | B10: CG | C10: 1 | D10: Lingua Portuguesa | E10: Figuras de linguagem | F10: Cobranca recorrente em provas FCC recentes | G10: Média | H10: Não estudado
A11: 10 | B11: CG | C11: 1 | D11: Lingua Portuguesa | E11: Morfossintaxe | F11: Base de varias questoes de gramatica FCC | G11: Alta | H11: Não estudado
A12: 11 | B12: CG | C12: 1 | D12: Lingua Portuguesa | E12: Elementos estruturais e processos de formacao de palavras | F12: Cobranca eventual | G12: Média | H12: Não estudado
A13: 12 | B13: CG | C13: 1 | D13: Lingua Portuguesa | E13: Sinonimia e antonimia | F13: Cobranca frequente ligada a vocabulario no texto | G13: Média | H13: Não estudado
... A254: 253 | B254: CE | C254: 2 | D254: Lingua Inglesa (Leitura Tecnica) | E254: Interpretacao de artigos tecnicos e documentacao de APIs | F254: Desdobramento do item anterior | G254: Baixa | H254: Não estudado

Sheet Resumo por Disciplina
A1: Disciplina | B1: Bloco | C1: Total de Itens | D1: Urgente | E1: Alta | F1: Média | G1: Baixa | H1: Não estudado | I1: Estudando | J1: Estudado | K1: Revisado | L1: % Concluído
A2: Lingua Portuguesa | B2: CG | C2: =COUNTIF('Edital Verticalizado'!$D:$D,$A2) -> 22 | D2: =COUNTIFS('Edital Verticalizado'!$D:$D,$A2,'Edital Verticalizado'!$G:$G,"Urgente") -> 2 | E2: =COUNTIFS('Edital Verticalizado'!$D:$D,$A2,'Edital Verticalizado'!$G:$G,"Alta") -> 10 | F2: =COUNTIFS('Edital Verticalizado'!$D:$D,$A2,'Edital Verticalizado'!$G:$G,"Média") -> 8 | G2: =COUNTIFS('Edital Verticalizado'!$D:$D,$A2,'Edital Verticalizado'!$G:$G,"Baixa") -> 2 | H2: =COUNTIFS('Edital Verticalizado'!$D:$D,$A2,'Edital Verticalizado'!$H:$H,"Não estudado") -> 21 | I2: =COUNTIFS('Edital Verticalizado'!$D:$D,$A2,'Edital Verticalizado'!$H:$H,"Estudando") -> 1 | J2: =COUNTIFS('Edital Verticalizado'!$D:$D,$A2,'Edital Verticalizado'!$H:$H,"Estudado") -> 0 | K2: =COUNTIFS('Edital Verticalizado'!$D:$D,$A2,'Edital Verticalizado'!$H:$H,"Revisado") -> 0 | L2: =IF(C2=0,0,(J2+K2)/C2) -> 0
A3: Matematica e Raciocinio Logico | B3: CG | C3: =COUNTIF('Edital Verticalizado'!$D:$D,$A3) -> 12 | D3: =COUNTIFS('Edital Verticalizado'!$D:$D,$A3,'Edital Verticalizado'!$G:$G,"Urgente") -> 1 | E3: =COUNTIFS('Edital Verticalizado'!$D:$D,$A3,'Edital Verticalizado'!$G:$G,"Alta") -> 5 | F3: =COUNTIFS('Edital Verticalizado'!$D:$D,$A3,'Edital Verticalizado'!$G:$G,"Média") -> 4 | G3: =COUNTIFS('Edital Verticalizado'!$D:$D,$A3,'Edital Verticalizado'!$G:$G,"Baixa") -> 2 | H3: =COUNTIFS('Edital Verticalizado'!$D:$D,$A3,'Edital Verticalizado'!$H:$H,"Não estudado") -> 12 | I3: =COUNTIFS('Edital Verticalizado'!$D:$D,$A3,'Edital Verticalizado'!$H:$H,"Estudando") -> 0 | J3: =COUNTIFS('Edital Verticalizado'!$D:$D,$A3,'Edital Verticalizado'!$H:$H,"Estudado") -> 0 | K3: =COUNTIFS('Edital Verticalizado'!$D:$D,$A3,'Edital Verticalizado'!$H:$H,"Revisado") -> 0 | L3: =IF(C3=0,0,(J3+K3)/C3) -> 0
A4: Legislacao Institucional | B4: CG | C4: =COUNTIF('Edital Verticalizado'!$D:$D,$A4) -> 17 | D4: =COUNTIFS('Edital Verticalizado'!$D:$D,$A4,'Edital Verticalizado'!$G:$G,"Urgente") -> 2 | E4: =COUNTIFS('Edital Verticalizado'!$D:$D,$A4,'Edital Verticalizado'!$G:$G,"Alta") -> 9 | F4: =COUNTIFS('Edital Verticalizado'!$D:$D,$A4,'Edital Verticalizado'!$G:$G,"Média") -> 6 | G4: =COUNTIFS('Edital Verticalizado'!$D:$D,$A4,'Edital Verticalizado'!$G:$G,"Baixa") -> 0 | H4: =COUNTIFS('Edital Verticalizado'!$D:$D,$A4,'Edital Verticalizado'!$H:$H,"Não estudado") -> 14 | I4: =COUNTIFS('Edital Verticalizado'!$D:$D,$A4,'Edital Verticalizado'!$H:$H,"Estudando") -> 3 | J4: =COUNTIFS('Edital Verticalizado'!$D:$D,$A4,'Edital Verticalizado'!$H:$H,"Estudado") -> 0 | K4: =COUNTIFS('Edital Verticalizado'!$D:$D,$A4,'Edital Verticalizado'!$H:$H,"Revisado") -> 0 | L4: =IF(C4=0,0,(J4+K4)/C4) -> 0
A5: Engenharia de Software | B5: CE | C5: =COUNTIF('Edital Verticalizado'!$D:$D,$A5) -> 32 | D5: =COUNTIFS('Edital Verticalizado'!$D:$D,$A5,'Edital Verticalizado'!$G:$G,"Urgente") -> 4 | E5: =COUNTIFS('Edital Verticalizado'!$D:$D,$A5,'Edital Verticalizado'!$G:$G,"Alta") -> 12 | F5: =COUNTIFS('Edital Verticalizado'!$D:$D,$A5,'Edital Verticalizado'!$G:$G,"Média") -> 15 | G5: =COUNTIFS('Edital Verticalizado'!$D:$D,$A5,'Edital Verticalizado'!$G:$G,"Baixa") -> 1 | H5: =COUNTIFS('Edital Verticalizado'!$D:$D,$A5,'Edital Verticalizado'!$H:$H,"Não estudado") -> 32 | I5: =COUNTIFS('Edital Verticalizado'!$D:$D,$A5,'Edital Verticalizado'!$H:$H,"Estudando") -> 0 | J5: =COUNTIFS('Edital Verticalizado'!$D:$D,$A5,'Edital Verticalizado'!$H:$H,"Estudado") -> 0 | K5: =COUNTIFS('Edital Verticalizado'!$D:$D,$A5,'Edital Verticalizado'!$H:$H,"Revisado") -> 0 | L5: =IF(C5=0,0,(J5+K5)/C5) -> 0
A6: Desenvolvimento de Sistemas | B6: CE | C6: =COUNTIF('Edital Verticalizado'!$D:$D,$A6) -> 24 | D6: =COUNTIFS('Edital Verticalizado'!$D:$D,$A6,'Edital Verticalizado'!$G:$G,"Urgente") -> 5 | E6: =COUNTIFS('Edital Verticalizado'!$D:$D,$A6,'Edital Verticalizado'!$G:$G,"Alta") -> 11 | F6: =COUNTIFS('Edital Verticalizado'!$D:$D,$A6,'Edital Verticalizado'!$G:$G,"Média") -> 7 | G6: =COUNTIFS('Edital Verticalizado'!$D:$D,$A6,'Edital Verticalizado'!$G:$G,"Baixa") -> 1 | H6: =COUNTIFS('Edital Verticalizado'!$D:$D,$A6,'Edital Verticalizado'!$H:$H,"Não estudado") -> 24 | I6: =COUNTIFS('Edital Verticalizado'!$D:$D,$A6,'Edital Verticalizado'!$H:$H,"Estudando") -> 0 | J6: =COUNTIFS('Edital Verticalizado'!$D:$D,$A6,'Edital Verticalizado'!$H:$H,"Estudado") -> 0 | K6: =COUNTIFS('Edital Verticalizado'!$D:$D,$A6,'Edital Verticalizado'!$H:$H,"Revisado") -> 0 | L6: =IF(C6=0,0,(J6+K6)/C6) -> 0
A7: Eng. de Software Assistida por IA e Sistemas Agentivos | B7: CE | C7: =COUNTIF('Edital Verticalizado'!$D:$D,$A7) -> 18 | D7: =COUNTIFS('Edital Verticalizado'!$D:$D,$A7,'Edital Verticalizado'!$G:$G,"Urgente") -> 0 | E7: =COUNTIFS('Edital Verticalizado'!$D:$D,$A7,'Edital Verticalizado'!$G:$G,"Alta") -> 9 | F7: =COUNTIFS('Edital Verticalizado'!$D:$D,$A7,'Edital Verticalizado'!$G:$G,"Média") -> 9 | G7: =COUNTIFS('Edital Verticalizado'!$D:$D,$A7,'Edital Verticalizado'!$G:$G,"Baixa") -> 0 | H7: =COUNTIFS('Edital Verticalizado'!$D:$D,$A7,'Edital Verticalizado'!$H:$H,"Não estudado") -> 18 | I7: =COUNTIFS('Edital Verticalizado'!$D:$D,$A7,'Edital Verticalizado'!$H:$H,"Estudando") -> 0 | J7: =COUNTIFS('Edital Verticalizado'!$D:$D,$A7,'Edital Verticalizado'!$H:$H,"Estudado") -> 0 | K7: =COUNTIFS('Edital Verticalizado'!$D:$D,$A7,'Edital Verticalizado'!$H:$H,"Revisado") -> 0 | L7: =IF(C7=0,0,(J7+K7)/C7) -> 0
A8: DevOps, Plataforma e Engenharia de Entrega | B8: CE | C8: =COUNTIF('Edital Verticalizado'!$D:$D,$A8) -> 15 | D8: =COUNTIFS('Edital Verticalizado'!$D:$D,$A8,'Edital Verticalizado'!$G:$G,"Urgente") -> 2 | E8: =COUNTIFS('Edital Verticalizado'!$D:$D,$A8,'Edital Verticalizado'!$G:$G,"Alta") -> 5 | F8: =COUNTIFS('Edital Verticalizado'!$D:$D,$A8,'Edital Verticalizado'!$G:$G,"Média") -> 8 | G8: =COUNTIFS('Edital Verticalizado'!$D:$D,$A8,'Edital Verticalizado'!$G:$G,"Baixa") -> 0 | H8: =COUNTIFS('Edital Verticalizado'!$D:$D,$A8,'Edital Verticalizado'!$H:$H,"Não estudado") -> 15 | I8: =COUNTIFS('Edital Verticalizado'!$D:$D,$A8,'Edital Verticalizado'!$H:$H,"Estudando") -> 0 | J8: =COUNTIFS('Edital Verticalizado'!$D:$D,$A8,'Edital Verticalizado'!$H:$H,"Estudado") -> 0 | K8: =COUNTIFS('Edital Verticalizado'!$D:$D,$A8,'Edital Verticalizado'!$H:$H,"Revisado") -> 0 | L8: =IF(C8=0,0,(J8+K8)/C8) -> 0
A9: Banco de Dados | B9: CE | C9: =COUNTIF('Edital Verticalizado'!$D:$D,$A9) -> 16 | D9: =COUNTIFS('Edital Verticalizado'!$D:$D,$A9,'Edital Verticalizado'!$G:$G,"Urgente") -> 4 | E9: =COUNTIFS('Edital Verticalizado'!$D:$D,$A9,'Edital Verticalizado'!$G:$G,"Alta") -> 6 | F9: =COUNTIFS('Edital Verticalizado'!$D:$D,$A9,'Edital Verticalizado'!$G:$G,"Média") -> 6 | G9: =COUNTIFS('Edital Verticalizado'!$D:$D,$A9,'Edital Verticalizado'!$G:$G,"Baixa") -> 0 | H9: =COUNTIFS('Edital Verticalizado'!$D:$D,$A9,'Edital Verticalizado'!$H:$H,"Não estudado") -> 14 | I9: =COUNTIFS('Edital Verticalizado'!$D:$D,$A9,'Edital Verticalizado'!$H:$H,"Estudando") -> 2 | J9: =COUNTIFS('Edital Verticalizado'!$D:$D,$A9,'Edital Verticalizado'!$H:$H,"Estudado") -> 0 | K9: =COUNTIFS('Edital Verticalizado'!$D:$D,$A9,'Edital Verticalizado'!$H:$H,"Revisado") -> 0 | L9: =IF(C9=0,0,(J9+K9)/C9) -> 0
A10: IA, Ciencia de Dados e Automacao | B10: CE | C10: =COUNTIF('Edital Verticalizado'!$D:$D,$A10) -> 17 | D10: =COUNTIFS('Edital Verticalizado'!$D:$D,$A10,'Edital Verticalizado'!$G:$G,"Urgente") -> 0 | E10: =COUNTIFS('Edital Verticalizado'!$D:$D,$A10,'Edital Verticalizado'!$G:$G,"Alta") -> 8 | F10: =COUNTIFS('Edital Verticalizado'!$D:$D,$A10,'Edital Verticalizado'!$G:$G,"Média") -> 8 | G10: =COUNTIFS('Edital Verticalizado'!$D:$D,$A10,'Edital Verticalizado'!$G:$G,"Baixa") -> 1 | H10: =COUNTIFS('Edital Verticalizado'!$D:$D,$A10,'Edital Verticalizado'!$H:$H,"Não estudado") -> 17 | I10: =COUNTIFS('Edital Verticalizado'!$D:$D,$A10,'Edital Verticalizado'!$H:$H,"Estudando") -> 0 | J10: =COUNTIFS('Edital Verticalizado'!$D:$D,$A10,'Edital Verticalizado'!$H:$H,"Estudado") -> 0 | K10: =COUNTIFS('Edital Verticalizado'!$D:$D,$A10,'Edital Verticalizado'!$H:$H,"Revisado") -> 0 | L10: =IF(C10=0,0,(J10+K10)/C10) -> 0
A11: Seguranca da Informacao | B11: CE | C11: =COUNTIF('Edital Verticalizado'!$D:$D,$A11) -> 23 | D11: =COUNTIFS('Edital Verticalizado'!$D:$D,$A11,'Edital Verticalizado'!$G:$G,"Urgente") -> 7 | E11: =COUNTIFS('Edital Verticalizado'!$D:$D,$A11,'Edital Verticalizado'!$G:$G,"Alta") -> 11 | F11: =COUNTIFS('Edital Verticalizado'!$D:$D,$A11,'Edital Verticalizado'!$G:$G,"Média") -> 5 | G11: =COUNTIFS('Edital Verticalizado'!$D:$D,$A11,'Edital Verticalizado'!$G:$G,"Baixa") -> 0 | H11: =COUNTIFS('Edital Verticalizado'!$D:$D,$A11,'Edital Verticalizado'!$H:$H,"Não estudado") -> 23 | I11: =COUNTIFS('Edital Verticalizado'!$D:$D,$A11,'Edital Verticalizado'!$H:$H,"Estudando") -> 0 | J11: =COUNTIFS('Edital Verticalizado'!$D:$D,$A11,'Edital Verticalizado'!$H:$H,"Estudado") -> 0 | K11: =COUNTIFS('Edital Verticalizado'!$D:$D,$A11,'Edital Verticalizado'!$H:$H,"Revisado") -> 0 | L11: =IF(C11=0,0,(J11+K11)/C11) -> 0
A12: Sistemas Operacionais, Redes e Computacao em Nuvem | B12: CE | C12: =COUNTIF('Edital Verticalizado'!$D:$D,$A12) -> 24 | D12: =COUNTIFS('Edital Verticalizado'!$D:$D,$A12,'Edital Verticalizado'!$G:$G,"Urgente") -> 6 | E12: =COUNTIFS('Edital Verticalizado'!$D:$D,$A12,'Edital Verticalizado'!$G:$G,"Alta") -> 10 | F12: =COUNTIFS('Edital Verticalizado'!$D:$D,$A12,'Edital Verticalizado'!$G:$G,"Média") -> 7 | G12: =COUNTIFS('Edital Verticalizado'!$D:$D,$A12,'Edital Verticalizado'!$G:$G,"Baixa") -> 1 | H12: =COUNTIFS('Edital Verticalizado'!$D:$D,$A12,'Edital Verticalizado'!$H:$H,"Não estudado") -> 24 | I12: =COUNTIFS('Edital Verticalizado'!$D:$D,$A12,'Edital Verticalizado'!$H:$H,"Estudando") -> 0 | J12: =COUNTIFS('Edital Verticalizado'!$D:$D,$A12,'Edital Verticalizado'!$H:$H,"Estudado") -> 0 | K12: =COUNTIFS('Edital Verticalizado'!$D:$D,$A12,'Edital Verticalizado'!$H:$H,"Revisado") -> 0 | L12: =IF(C12=0,0,(J12+K12)/C12) -> 0
A13: Governanca de Tecnologia da Informacao | B13: CE | C13: =COUNTIF('Edital Verticalizado'!$D:$D,$A13) -> 16 | D13: =COUNTIFS('Edital Verticalizado'!$D:$D,$A13,'Edital Verticalizado'!$G:$G,"Urgente") -> 5 | E13: =COUNTIFS('Edital Verticalizado'!$D:$D,$A13,'Edital Verticalizado'!$G:$G,"Alta") -> 6 | F13: =COUNTIFS('Edital Verticalizado'!$D:$D,$A13,'Edital Verticalizado'!$G:$G,"Média") -> 5 | G13: =COUNTIFS('Edital Verticalizado'!$D:$D,$A13,'Edital Verticalizado'!$G:$G,"Baixa") -> 0 | H13: =COUNTIFS('Edital Verticalizado'!$D:$D,$A13,'Edital Verticalizado'!$H:$H,"Não estudado") -> 16 | I13: =COUNTIFS('Edital Verticalizado'!$D:$D,$A13,'Edital Verticalizado'!$H:$H,"Estudando") -> 0 | J13: =COUNTIFS('Edital Verticalizado'!$D:$D,$A13,'Edital Verticalizado'!$H:$H,"Estudado") -> 0 | K13: =COUNTIFS('Edital Verticalizado'!$D:$D,$A13,'Edital Verticalizado'!$H:$H,"Revisado") -> 0 | L13: =IF(C13=0,0,(J13+K13)/C13) -> 0
... A15: Lingua Inglesa (Leitura Tecnica) | B15: CE | C15: =COUNTIF('Edital Verticalizado'!$D:$D,$A15) -> 4 | D15: =COUNTIFS('Edital Verticalizado'!$D:$D,$A15,'Edital Verticalizado'!$G:$G,"Urgente") -> 0 | E15: =COUNTIFS('Edital Verticalizado'!$D:$D,$A15,'Edital Verticalizado'!$G:$G,"Alta") -> 0 | F15: =COUNTIFS('Edital Verticalizado'!$D:$D,$A15,'Edital Verticalizado'!$G:$G,"Média") -> 3 | G15: =COUNTIFS('Edital Verticalizado'!$D:$D,$A15,'Edital Verticalizado'!$G:$G,"Baixa") -> 1 | H15: =COUNTIFS('Edital Verticalizado'!$D:$D,$A15,'Edital Verticalizado'!$H:$H,"Não estudado") -> 4 | I15: =COUNTIFS('Edital Verticalizado'!$D:$D,$A15,'Edital Verticalizado'!$H:$H,"Estudando") -> 0 | J15: =COUNTIFS('Edital Verticalizado'!$D:$D,$A15,'Edital Verticalizado'!$H:$H,"Estudado") -> 0 | K15: =COUNTIFS('Edital Verticalizado'!$D:$D,$A15,'Edital Verticalizado'!$H:$H,"Revisado") -> 0 | L15: =IF(C15=0,0,(J15+K15)/C15) -> 0
A16: TOTAL | C16: =SUM(C2:C15) -> 253 | D16: =SUM(D2:D15) -> 39 | E16: =SUM(E2:E15) -> 111 | F16: =SUM(F2:F15) -> 94 | G16: =SUM(G2:G15) -> 9 | H16: =SUM(H2:H15) -> 247 | I16: =SUM(I2:I15) -> 6 | J16: =SUM(J2:J15) -> 0 | K16: =SUM(K2:K15) -> 0 | L16: =IF(C16=0,0,(J16+K16)/C16) -> 0
